db_query_mcp/factory.py
db_query_mcp/main.py
db_query_mcp/db_adapters/base_adapter.py
db_query_mcp/db_adapters/elasticsearch_db_adapter.py
db_query_mcp/db_adapters/relational_db_adapter.py
db_query_mcp/prompts/elasticsearch_db_prompt.py
db_query_mcp/prompts/relational_db_prompt.py
iflow_mcp_db_query_mcp-0.0.7.dist-info/licenses/LICENSE
iflow_mcp_db_query_mcp-0.0.7.dist-info/METADATA
iflow_mcp_db_query_mcp-0.0.7.dist-info/WHEEL
iflow_mcp_db_query_mcp-0.0.7.dist-info/entry_points.txt
iflow_mcp_db_query_mcp-0.0.7.dist-info/top_level.txt
iflow_mcp_db_query_mcp-0.0.7.dist-info/RECORD
