Metadata-Version: 2.4
Name: iflow-mcp_db-query-mcp
Version: 0.0.7
Summary: db-query-mcp is an MCP tool that enables data querying and export operations across diverse databases. 
Author-email: zhangshulin <zhangslwork@yeah.net>
License-Expression: Apache-2.0
Project-URL: repository, https://github.com/NewToolAI/db-query-mcp
Requires-Python: >=3.10
License-File: LICENSE
Requires-Dist: mcp[cli]>=1.9.0
Requires-Dist: sqlalchemy>=2.0.0
Dynamic: license-file
